pix_to_xls/__init__.py
pix_to_xls/builder.py
pix_to_xls/cli.py
pix_to_xls-1.0.1.dist-info/METADATA
pix_to_xls-1.0.1.dist-info/WHEEL
pix_to_xls-1.0.1.dist-info/entry_points.txt
pix_to_xls-1.0.1.dist-info/top_level.txt
pix_to_xls-1.0.1.dist-info/RECORD
